LICENSE
README.md
setup.py
mulanai/__init__.py
mulanai/version.py
mulanai.egg-info/PKG-INFO
mulanai.egg-info/SOURCES.txt
mulanai.egg-info/dependency_links.txt
mulanai.egg-info/entry_points.txt
mulanai.egg-info/not-zip-safe
mulanai.egg-info/requires.txt
mulanai.egg-info/top_level.txt